stampa/__init__.py
stampa/stampa.py
stampa-0.2.0.dist-info/LICENSE
stampa-0.2.0.dist-info/METADATA
stampa-0.2.0.dist-info/WHEEL
stampa-0.2.0.dist-info/top_level.txt
stampa-0.2.0.dist-info/RECORD
