Metadata-Version: 2.1
Name: stampa
Version: 0.2.0
Summary: Generates date time as string without spaces
Author-email: Evzen Ptacek <p1463k@gmail.com>
Project-URL: Homepage, https://github.com/3p1463k/stampa
Project-URL: Bug Tracker, https://github.com/3p1463k/stampa/issues
Classifier: Programming Language :: Python :: 3
Classifier: License :: OSI Approved :: MIT License
Classifier: Operating System :: OS Independent
Requires-Python: >=3.7
License-File: LICENSE
